.gitignore
LICENSE
README.rst
setup.py
bin/pythonwarrior
pythonwarrior/__init__.py
pythonwarrior/config.py
pythonwarrior/floor.py
pythonwarrior/game.py
pythonwarrior/level.py
pythonwarrior/level_loader.py
pythonwarrior/player_generator.py
pythonwarrior/position.py
pythonwarrior/profile.py
pythonwarrior/runner.py
pythonwarrior/space.py
pythonwarrior/tower.py
pythonwarrior/turn.py
pythonwarrior/ui.py
pythonwarrior.egg-info/PKG-INFO
pythonwarrior.egg-info/SOURCES.txt
pythonwarrior.egg-info/dependency_links.txt
pythonwarrior.egg-info/requires.txt
pythonwarrior.egg-info/top_level.txt
pythonwarrior/abilities/__init__.py
pythonwarrior/abilities/attack.py
pythonwarrior/abilities/base.py
pythonwarrior/abilities/bind.py
pythonwarrior/abilities/detonate.py
pythonwarrior/abilities/direction_of.py
pythonwarrior/abilities/direction_of_stairs.py
pythonwarrior/abilities/distance_of.py
pythonwarrior/abilities/explode.py
pythonwarrior/abilities/feel.py
pythonwarrior/abilities/health.py
pythonwarrior/abilities/listen.py
pythonwarrior/abilities/look.py
pythonwarrior/abilities/pivot.py
pythonwarrior/abilities/rescue.py
pythonwarrior/abilities/rest.py
pythonwarrior/abilities/shoot.py
pythonwarrior/abilities/walk.py
pythonwarrior/templates/README
pythonwarrior/templates/__init__.py
pythonwarrior/templates/player.py
pythonwarrior/tests/__init__.py
pythonwarrior/tests/test_floor.py
pythonwarrior/tests/test_game.py
pythonwarrior/tests/test_level.py
pythonwarrior/tests/test_level_loader.py
pythonwarrior/tests/test_player_generator.py
pythonwarrior/tests/test_position.py
pythonwarrior/tests/test_profile.py
pythonwarrior/tests/test_space.py
pythonwarrior/tests/test_tower.py
pythonwarrior/tests/test_turn.py
pythonwarrior/tests/test_ui.py
pythonwarrior/tests/abilities/__init__.py
pythonwarrior/tests/abilities/test_attack.py
pythonwarrior/tests/abilities/test_base.py
pythonwarrior/tests/abilities/test_bind.py
pythonwarrior/tests/abilities/test_detonate.py
pythonwarrior/tests/abilities/test_direction_of.py
pythonwarrior/tests/abilities/test_direction_of_stairs.py
pythonwarrior/tests/abilities/test_distance_of.py
pythonwarrior/tests/abilities/test_explode.py
