Metadata-Version: 1.1
Name: pythonwarrior
Version: 0.0.5
Summary: Game written in Python for learning Python and AI - a Python port of ruby-warrior
Home-page: https://github.com/arbylee/python-warrior
Author: Richard Lee
Author-email: rblee88@gmail.com
License: MIT
Keywords: python ruby warrior rubywarrior pythonwarrior
Platform: UNKNOWN
Classifier: Programming Language :: Python
Classifier: License :: OSI Approved :: MIT License
Classifier: Development Status :: 3 - Alpha
